LICENSE
MANIFEST.in
README.md
notes.json
setup.py
assistance_bot.egg-info/PKG-INFO
assistance_bot.egg-info/SOURCES.txt
assistance_bot.egg-info/dependency_links.txt
assistance_bot.egg-info/entry_points.txt
assistance_bot.egg-info/requires.txt
assistance_bot.egg-info/top_level.txt
bot_folder/__init__.py
bot_folder/clean_folder.py
bot_folder/export_func.py
bot_folder/intellect_input.py
bot_folder/module_classes_2.py
bot_folder/module_classes_note.py
bot_folder/start_bot.py
bot_folder/test.py