Metadata-Version: 2.1
Name: assistance-bot
Version: 0.0.1
Summary: assistance_bot
Home-page: https://github.com/melser68/my-bot
Author: Python Core12 Team2
Author-email: msprivate68@gmail.com
License: MIT
Platform: UNKNOWN
License-File: LICENSE
